{
  "nexfi": [
    {
      "adhoc0": "0E:03:01:00:10:3D",
      "br-lan": "3E:03:01:00:10:3D",
      "eth1": "1E:03:01:00:10:3D",
      "ipaddress": "192.168.100.61",
      "no": "61"
    },
    {
      "adhoc0": "0E:03:01:00:10:3C",
      "br-lan": "3E:03:01:00:10:3C",
      "eth1": "1E:03:01:00:10:3C",
      "ipaddress": "192.168.100.60",
      "no": "60"
    },
    {
      "adhoc0": "0E:03:01:00:10:3E",
      "br-lan": "3E:03:01:00:10:3E",
      "eth1": "1E:03:01:00:10:3E",
      "ipaddress": "192.168.100.62",
      "no": "62"
    }
  ]
}
